README.rst
setup.py
ojson/__init__.py
ojson/ojson.py
ojson.egg-info/PKG-INFO
ojson.egg-info/SOURCES.txt
ojson.egg-info/dependency_links.txt
ojson.egg-info/top_level.txt